<?xml version="1.0" encoding="UTF-8"?>
<ZOO>
    <soldi>114</soldi>
    <clock/>
    <leoni>
        <vita>90</vita>
        <descrizione>Il leone è un possente felino appartenente alla famiglia dei leoni e noto come il re della giungla. È uno dei più grandi carnivori terrestri esistenti e si distingue per la sua possente struttura fisica, la criniera caratteristica e l'imponente presenza.</descrizione>
        <Leone 1>
            <nome>Leone 1</nome>
            <eta>11</eta>
            <peso>131.000000</peso>
            <cibo>Carne</cibo>
            <ruggito>86</ruggito>
            <criniera>0</criniera>
        </Leone 1>
        <Leone 2>
            <nome>Leone 2</nome>
            <eta>12</eta>
            <peso>153.000000</peso>
            <cibo>Carne</cibo>
            <ruggito>106</ruggito>
            <criniera>0</criniera>
        </Leone 2>
        <Leone 3>
            <nome>Leone 3</nome>
            <eta>12</eta>
            <peso>161.000000</peso>
            <cibo>Carne</cibo>
            <ruggito>60</ruggito>
            <criniera>0</criniera>
        </Leone 3>
    </leoni>
    <coccodrilli>
        <vita>100</vita>
    </coccodrilli>
    <pavoni>
        <vita>100</vita>
    </pavoni>
    <tartarughe>
        <vita>100</vita>
    </tartarughe>
    <struzzi>
        <vita>92</vita>
        <descrizione>Lo struzzo comune semplicemente struzzo, è una grande specie di uccello incapace di volare originario delle vaste savane dell'Africa.</descrizione>
        <Struzzo 1>
            <nome>Struzzo 1</nome>
            <eta>50</eta>
            <peso>78.000000</peso>
            <cibo>Erba</cibo>
            <velocita>47.000000</velocita>
        </Struzzo 1>
        <Struzzo 2>
            <nome>Struzzo 2</nome>
            <eta>42</eta>
            <peso>74.000000</peso>
            <cibo>Erba</cibo>
            <velocita>66.000000</velocita>
        </Struzzo 2>
        <Struzzo 3>
            <nome>Struzzo 3</nome>
            <eta>41</eta>
            <peso>92.000000</peso>
            <cibo>Erba</cibo>
            <velocita>57.000000</velocita>
        </Struzzo 3>
    </struzzi>
    <giraffe>
        <vita>100</vita>
    </giraffe>
</ZOO>
